dac_sim/__init__.py
dac_sim/cli.py
dac_sim/grid.py
dac_sim/molecule.py
dac_sim/molecule_dynamic.py
dac_sim/optimize.py
dac_sim/widom_insertion.py
dac_sim/models/README.md
dac_sim/models/mace-dac-1.model
dac_sim/scripts/__init__.py
dac_sim/scripts/run_md.py
dac_sim/scripts/run_opt.py
dac_sim/scripts/run_widom.py
dac_sim-0.0.3.dist-info/LICENSE
dac_sim-0.0.3.dist-info/METADATA
dac_sim-0.0.3.dist-info/WHEEL
dac_sim-0.0.3.dist-info/entry_points.txt
dac_sim-0.0.3.dist-info/top_level.txt
dac_sim-0.0.3.dist-info/RECORD
