Metadata-Version: 2.1
Name: dac-sim
Version: 0.0.3
Summary: UNKNOWN
Home-page: UNKNOWN
License: UNKNOWN
Platform: UNKNOWN
License-File: LICENSE
Requires-Dist: tqdm
Requires-Dist: mace-torch==0.3.6
Requires-Dist: torch-dftd
Requires-Dist: ase
Requires-Dist: MDAnalysis
Requires-Dist: fire
Requires-Dist: jupyterlab
Requires-Dist: click
